loginspect/__init__.py
loginspect/endpoint.py
pbu_log_inspector-0.0.2.dist-info/METADATA
pbu_log_inspector-0.0.2.dist-info/WHEEL
pbu_log_inspector-0.0.2.dist-info/top_level.txt
pbu_log_inspector-0.0.2.dist-info/RECORD
